price_val_engine/VERSION
price_val_engine/__init__.py
price_val_engine/__main__.py
price_val_engine/cmd.py
price_val_engine/commands/__init__.py
price_val_engine/commands/startproject.py
price_val_engine/commands/validate.py
price_val_engine/conf/__init__.py
price_val_engine/conf/default_settings.py
price_val_engine/conf/project_template/run.py.tmpl
price_val_engine/conf/project_template/project_name/__init__.py
price_val_engine/conf/project_template/project_name/settings.py.tmpl
price_val_engine/conf/project_template/project_name/validation_rules.py.tmpl
price_val_engine/core/__init__.py
price_val_engine/core/engine.py
price_val_engine/core/exceptions.py
price_val_engine/core/utils.py
price_val_engine/core/data/__init__.py
price_val_engine/core/data/reader.py
price_val_engine/core/data/writer.py
price_val_engine/core/validations/__init__.py
price_val_engine/core/validations/base_rules.py
price_val_engine/core/validations/general_rules.py
price_val_engine/core/validations/revision_rules.py
price_val_engine-0.1.10.dist-info/METADATA
price_val_engine-0.1.10.dist-info/WHEEL
price_val_engine-0.1.10.dist-info/top_level.txt
price_val_engine-0.1.10.dist-info/RECORD
