Metadata-Version: 2.1
Name: price-val-engine
Version: 0.1.10
Summary: last price revision validation rules
Author: Chandan Kumar Ojha
Author-email: mr.chandanojha@gmail.com
License: MIT
Requires-Python: >=3.6
Requires-Dist: boto3 (>=1.21.45)
Requires-Dist: botocore (>=1.24.45)
Requires-Dist: fsspec (>=2022.1.0)
Requires-Dist: slack-sdk (>=3.16.2)
